han/__init__.py
han/数学.py
han-0.1.2.dist-info/WHEEL
han-0.1.2.dist-info/METADATA
han-0.1.2.dist-info/RECORD
