Metadata-Version: 2.1
Name: han
Version: 0.1.2
Summary: aaaaaaaaaa
Home-page: https://github.com/piqizhu/han
Keywords: aa,bb,cc
Author: piqizhu
Requires-Python: >=3.8,<4.0
Classifier: Programming Language :: Python :: 3
Classifier: Programming Language :: Python :: 3.8
Classifier: Programming Language :: Python :: 3.9
Project-URL: Repository, https://github.com/piqizhu/han
